{"id":"korg_volca_bass","name":"volca bass","abbr":"KR","manufacturer":"KORG","parameters":[{"type":"cc","name":"Slide time","abbr":"SlTm","minimum":0,"maximum":127,"default_value":0,"nr1":5,"nr2":0,"value_labels":[]},{"type":"cc","name":"Expression","abbr":"Expr","minimum":0,"maximum":127,"default_value":0,"nr1":11,"nr2":0,"value_labels":[]},{"type":"cc","name":"Octave","abbr":"Octv","minimum":0,"maximum":127,"default_value":0,"nr1":40,"nr2":0,"value_labels":[]},{"type":"cc","name":"LFO rate","abbr":"LfRt","minimum":0,"maximum":127,"default_value":0,"nr1":41,"nr2":0,"value_labels":[]},{"type":"cc","name":"LFO intensity","abbr":"LfIn","minimum":0,"maximum":127,"default_value":0,"nr1":42,"nr2":0,"value_labels":[]},{"type":"cc","name":"VCO pitch 1","abbr":"VP1","minimum":0,"maximum":127,"default_value":0,"nr1":43,"nr2":0,"value_labels":[]},{"type":"cc","name":"VCO pitch 2","abbr":"VP2","minimum":0,"maximum":127,"default_value":0,"nr1":44,"nr2":0,"value_labels":[]},{"type":"cc","name":"VCO pitch 3","abbr":"VP3","minimum":0,"maximum":127,"default_value":0,"nr1":45,"nr2":0,"value_labels":[]},{"type":"cc","name":"EG attack","abbr":"EgAt","minimum":0,"maximum":127,"default_value":0,"nr1":46,"nr2":0,"value_labels":[]},{"type":"cc","name":"EG decay/release","abbr":"EgDc","minimum":0,"maximum":127,"default_value":0,"nr1":47,"nr2":0,"value_labels":[]},{"type":"cc","name":"Cutoff EG intensity","abbr":"CEIn","minimum":0,"maximum":127,"default_value":0,"nr1":48,"nr2":0,"value_labels":[]},{"type":"cc","name":"Gate time","abbr":"GtTm","minimum":0,"maximum":127,"default_value":0,"nr1":49,"nr2":0,"value_labels":[]}],"script":null}