{"id":"korg_volca_fm","name":"volca fm","abbr":"KR","manufacturer":"KORG","parameters":[{"type":"cc","name":"Transpose","abbr":"Trns","minimum":0,"maximum":127,"default_value":0,"nr1":null,"nr2":40,"value_labels":[]},{"type":"cc","name":"Velocity","abbr":"Vlct","minimum":0,"maximum":127,"default_value":0,"nr1":null,"nr2":41,"value_labels":[]},{"type":"cc","name":"Modulator attack","abbr":"MdAt","minimum":0,"maximum":127,"default_value":0,"nr1":null,"nr2":42,"value_labels":[]},{"type":"cc","name":"Modulator decay","abbr":"MdDc","minimum":0,"maximum":127,"default_value":0,"nr1":null,"nr2":43,"value_labels":[]},{"type":"cc","name":"Carrier attack","abbr":"CrAt","minimum":0,"maximum":127,"default_value":0,"nr1":null,"nr2":44,"value_labels":[]},{"type":"cc","name":"Carrier decay","abbr":"CrDc","minimum":0,"maximum":127,"default_value":0,"nr1":null,"nr2":45,"value_labels":[]},{"type":"cc","name":"LFO rate","abbr":"LfRt","minimum":0,"maximum":127,"default_value":0,"nr1":null,"nr2":46,"value_labels":[]},{"type":"cc","name":"LFO pitch depth","abbr":"LPDp","minimum":0,"maximum":127,"default_value":0,"nr1":null,"nr2":47,"value_labels":[]},{"type":"cc","name":"Algorithm","abbr":"Algr","minimum":0,"maximum":127,"default_value":0,"nr1":null,"nr2":48,"value_labels":[]},{"type":"cc","name":"Arpeggiator type","abbr":"ArTy","minimum":0,"maximum":127,"default_value":0,"nr1":null,"nr2":48,"value_labels":[]},{"type":"cc","name":"Arpeggiator div","abbr":"ArDv","minimum":0,"maximum":127,"default_value":0,"nr1":null,"nr2":50,"value_labels":[]}],"script":null}