{"id":"roland_sh_01a","name":"SH-01A","abbr":"Rl","manufacturer":"Roland","parameters":[{"type":"cc","name":"Modulation","abbr":"Mdlt","minimum":0,"maximum":127,"default_value":0,"nr1":null,"nr2":1,"value_labels":[]},{"type":"cc","name":"Portamento time","abbr":"PrTm","minimum":0,"maximum":127,"default_value":0,"nr1":null,"nr2":5,"value_labels":[]},{"type":"cc","name":"Expression pedal","abbr":"ExPd","minimum":0,"maximum":127,"default_value":0,"nr1":null,"nr2":11,"value_labels":[]},{"type":"cc","name":"Portament mode","abbr":"PrMd","minimum":0,"maximum":127,"default_value":0,"nr1":null,"nr2":31,"value_labels":[]},{"type":"cc","name":"Hold","abbr":"Hold","minimum":0,"maximum":127,"default_value":0,"nr1":null,"nr2":64,"value_labels":[]},{"type":"cc","name":"Portamento","abbr":"Prtm","minimum":0,"maximum":127,"default_value":0,"nr1":null,"nr2":65,"value_labels":[]},{"type":"cc","name":"Tune","abbr":"Tune","minimum":0,"maximum":127,"default_value":0,"nr1":null,"nr2":76,"value_labels":[]},{"type":"cc","name":"Transpose SW","abbr":"TrSw","minimum":0,"maximum":127,"default_value":0,"nr1":null,"nr2":77,"value_labels":[]},{"type":"cc","name":"Noise mode","abbr":"NsMd","minimum":0,"maximum":127,"default_value":0,"nr1":null,"nr2":78,"value_labels":[]},{"type":"cc","name":"Assign mode","abbr":"AsMd","minimum":0,"maximum":127,"default_value":0,"nr1":null,"nr2":80,"value_labels":[]},{"type":"cc","name":"LFO rate","abbr":"LfRt","minimum":0,"maximum":127,"default_value":0,"nr1":null,"nr2":3,"value_labels":[]},{"type":"cc","name":"LFO mode","abbr":"LfMd","minimum":0,"maximum":127,"default_value":0,"nr1":null,"nr2":79,"value_labels":[]},{"type":"cc","name":"LFO wave form","abbr":"LWFr","minimum":0,"maximum":127,"default_value":0,"nr1":null,"nr2":12,"value_labels":[]},{"type":"cc","name":"VCO modulation depth","abbr":"VMDp","minimum":0,"maximum":127,"default_value":0,"nr1":null,"nr2":13,"value_labels":[]},{"type":"cc","name":"VCO range","abbr":"VcRn","minimum":0,"maximum":127,"default_value":0,"nr1":null,"nr2":14,"value_labels":[]},{"type":"cc","name":"VCO pulse width","abbr":"VPWd","minimum":0,"maximum":127,"default_value":0,"nr1":null,"nr2":15,"value_labels":[]},{"type":"cc","name":"VCO PWM source","abbr":"VPSr","minimum":0,"maximum":127,"default_value":0,"nr1":null,"nr2":16,"value_labels":[]},{"type":"cc","name":"VCO mod sens","abbr":"VMSn","minimum":0,"maximum":127,"default_value":0,"nr1":null,"nr2":17,"value_labels":[]},{"type":"cc","name":"VCO bend depth","abbr":"VBDp","minimum":0,"maximum":127,"default_value":0,"nr1":null,"nr2":18,"value_labels":[]},{"type":"cc","name":"VCO PWM level","abbr":"VPLv","minimum":0,"maximum":127,"default_value":0,"nr1":null,"nr2":19,"value_labels":[]},{"type":"cc","name":"VCO saw level","abbr":"VSLv","minimum":0,"maximum":127,"default_value":0,"nr1":null,"nr2":20,"value_labels":[]},{"type":"cc","name":"VCO sub level","abbr":"VSLv","minimum":0,"maximum":127,"default_value":0,"nr1":null,"nr2":21,"value_labels":[]},{"type":"cc","name":"VCO sub type","abbr":"VSTy","minimum":0,"maximum":127,"default_value":0,"nr1":null,"nr2":22,"value_labels":[]},{"type":"cc","name":"VCO noise level","abbr":"VNLv","minimum":0,"maximum":127,"default_value":0,"nr1":null,"nr2":23,"value_labels":[]},{"type":"cc","name":"VCF envelope depth","abbr":"VEDp","minimum":0,"maximum":127,"default_value":0,"nr1":null,"nr2":24,"value_labels":[]},{"type":"cc","name":"VCF modulation depth","abbr":"VMDp","minimum":0,"maximum":127,"default_value":0,"nr1":null,"nr2":25,"value_labels":[]},{"type":"cc","name":"VCF key follow","abbr":"VKFl","minimum":0,"maximum":127,"default_value":0,"nr1":null,"nr2":26,"value_labels":[]},{"type":"cc","name":"VCF cutoff","abbr":"VcCt","minimum":0,"maximum":127,"default_value":0,"nr1":null,"nr2":74,"value_labels":[]},{"type":"cc","name":"VCF resonance","abbr":"VcRs","minimum":0,"maximum":127,"default_value":0,"nr1":null,"nr2":71,"value_labels":[]},{"type":"cc","name":"VCF bend depth","abbr":"VBDp","minimum":0,"maximum":127,"default_value":0,"nr1":null,"nr2":27,"value_labels":[]},{"type":"cc","name":"VCA envelope SW","abbr":"VESw","minimum":0,"maximum":127,"default_value":0,"nr1":null,"nr2":28,"value_labels":[]},{"type":"cc","name":"VCA envelope mode","abbr":"VEMd","minimum":0,"maximum":127,"default_value":0,"nr1":null,"nr2":29,"value_labels":[]},{"type":"cc","name":"Envelope attack","abbr":"EnAt","minimum":0,"maximum":127,"default_value":0,"nr1":null,"nr2":73,"value_labels":[]},{"type":"cc","name":"Envelope sustain","abbr":"EnSs","minimum":0,"maximum":127,"default_value":0,"nr1":null,"nr2":30,"value_labels":[]},{"type":"cc","name":"Envelope decay","abbr":"EnDc","minimum":0,"maximum":127,"default_value":0,"nr1":null,"nr2":75,"value_labels":[]},{"type":"cc","name":"Envelope release","abbr":"EnRl","minimum":0,"maximum":127,"default_value":0,"nr1":null,"nr2":72,"value_labels":[]},{"type":"cc","name":"Chord voice 2 SW","abbr":"CV2S","minimum":0,"maximum":127,"default_value":0,"nr1":null,"nr2":81,"value_labels":[]},{"type":"cc","name":"Chord voice 3 SW","abbr":"CV3S","minimum":0,"maximum":127,"default_value":0,"nr1":null,"nr2":82,"value_labels":[]},{"type":"cc","name":"Chord voice 4 SW","abbr":"CV4S","minimum":0,"maximum":127,"default_value":0,"nr1":null,"nr2":83,"value_labels":[]},{"type":"cc","name":"Chord voice 2 key shift","abbr":"CV2K","minimum":0,"maximum":127,"default_value":0,"nr1":null,"nr2":85,"value_labels":[]},{"type":"cc","name":"Chord voice 3 key shift","abbr":"CV3K","minimum":0,"maximum":127,"default_value":0,"nr1":null,"nr2":86,"value_labels":[]},{"type":"cc","name":"Chord voice 4 key shift","abbr":"CV4K","minimum":0,"maximum":127,"default_value":0,"nr1":null,"nr2":87,"value_labels":[]}],"script":null}