{"id":"strymon_nightsky","name":"Nightsky","abbr":"St","manufacturer":"Strymon","parameters":[{"type":"cc","name":"Reverb Level","abbr":"RvLv","minimum":0,"maximum":127,"default_value":0,"nr1":null,"nr2":11,"value_labels":[]},{"type":"cc","name":"DRY Level","abbr":"DrLv","minimum":0,"maximum":127,"default_value":0,"nr1":null,"nr2":12,"value_labels":[]},{"type":"cc","name":"MOD Speed","abbr":"MdSp","minimum":0,"maximum":127,"default_value":0,"nr1":null,"nr2":13,"value_labels":[]},{"type":"cc","name":"MOD Target","abbr":"MdTr","minimum":0,"maximum":127,"default_value":0,"nr1":null,"nr2":14,"value_labels":[]},{"type":"cc","name":"MOD Depth","abbr":"MdDp","minimum":0,"maximum":127,"default_value":0,"nr1":null,"nr2":15,"value_labels":[]},{"type":"cc","name":"MOD Shape","abbr":"MdSh","minimum":0,"maximum":127,"default_value":0,"nr1":null,"nr2":16,"value_labels":[]},{"type":"cc","name":"PRE Delay","abbr":"PrDl","minimum":0,"maximum":127,"default_value":0,"nr1":null,"nr2":17,"value_labels":[]},{"type":"cc","name":"Decay Length","abbr":"DcLn","minimum":0,"maximum":127,"default_value":0,"nr1":null,"nr2":18,"value_labels":[]},{"type":"cc","name":"Decay Texture","abbr":"DcTx","minimum":0,"maximum":127,"default_value":0,"nr1":null,"nr2":19,"value_labels":[]},{"type":"cc","name":"Decay Size Pitch","abbr":"DSPt","minimum":0,"maximum":127,"default_value":0,"nr1":null,"nr2":20,"value_labels":[]},{"type":"cc","name":"Decay Quantize","abbr":"DcQn","minimum":0,"maximum":127,"default_value":0,"nr1":null,"nr2":21,"value_labels":[]},{"type":"cc","name":"Tone LOW CUT","abbr":"TLCt","minimum":0,"maximum":127,"default_value":0,"nr1":null,"nr2":22,"value_labels":[]},{"type":"cc","name":"Tone High CUT","abbr":"THCt","minimum":0,"maximum":127,"default_value":0,"nr1":null,"nr2":23,"value_labels":[]},{"type":"cc","name":"Tone Filter","abbr":"TnFl","minimum":0,"maximum":127,"default_value":0,"nr1":null,"nr2":24,"value_labels":[]},{"type":"cc","name":"Tone Lowpass Q","abbr":"TLQ","minimum":0,"maximum":127,"default_value":0,"nr1":null,"nr2":25,"value_labels":[]},{"type":"cc","name":"Voice Interval","abbr":"VcIn","minimum":0,"maximum":127,"default_value":0,"nr1":null,"nr2":26,"value_labels":[]},{"type":"cc","name":"Voice Scale Select","abbr":"VSSl","minimum":0,"maximum":127,"default_value":0,"nr1":null,"nr2":27,"value_labels":[]},{"type":"cc","name":"Voice Shimmer","abbr":"VcSh","minimum":0,"maximum":127,"default_value":0,"nr1":null,"nr2":28,"value_labels":[]},{"type":"cc","name":"Voice Shimmer Level","abbr":"VSLv","minimum":0,"maximum":127,"default_value":0,"nr1":null,"nr2":29,"value_labels":[]},{"type":"cc","name":"Voice Glimmer","abbr":"VcGl","minimum":0,"maximum":127,"default_value":0,"nr1":null,"nr2":30,"value_labels":[]},{"type":"cc","name":"Voice Glimmer Gain","abbr":"VGGn","minimum":0,"maximum":127,"default_value":0,"nr1":null,"nr2":31,"value_labels":[]},{"type":"cc","name":"Voice Drive","abbr":"VcDr","minimum":0,"maximum":127,"default_value":0,"nr1":null,"nr2":33,"value_labels":[]},{"type":"cc","name":"Voice Drive Level","abbr":"VDLv","minimum":0,"maximum":127,"default_value":0,"nr1":null,"nr2":34,"value_labels":[]},{"type":"cc","name":"Freeze","abbr":"Frz","minimum":0,"maximum":127,"default_value":0,"nr1":null,"nr2":35,"value_labels":[]},{"type":"cc","name":"Morph","abbr":"Mrph","minimum":0,"maximum":127,"default_value":0,"nr1":null,"nr2":36,"value_labels":[]},{"type":"cc","name":"Morph Speed","abbr":"MrSp","minimum":0,"maximum":127,"default_value":0,"nr1":null,"nr2":37,"value_labels":[]},{"type":"cc","name":"Sequence Mode","abbr":"SqMd","minimum":0,"maximum":127,"default_value":0,"nr1":null,"nr2":41,"value_labels":[]},{"type":"cc","name":"Sequencer Step1 OFF ON","abbr":"SSOO","minimum":0,"maximum":127,"default_value":0,"nr1":null,"nr2":42,"value_labels":[]},{"type":"cc","name":"Sequencer Step2 OFF ON","abbr":"SSOO","minimum":0,"maximum":127,"default_value":0,"nr1":null,"nr2":43,"value_labels":[]},{"type":"cc","name":"Sequencer Step3 OFF ON","abbr":"SSOO","minimum":0,"maximum":127,"default_value":0,"nr1":null,"nr2":44,"value_labels":[]},{"type":"cc","name":"Sequencer Step4 OFF ON","abbr":"SSOO","minimum":0,"maximum":127,"default_value":0,"nr1":null,"nr2":45,"value_labels":[]},{"type":"cc","name":"Sequencer Step5 OFF ON","abbr":"SSOO","minimum":0,"maximum":127,"default_value":0,"nr1":null,"nr2":46,"value_labels":[]},{"type":"cc","name":"Sequencer Step6 OFF ON","abbr":"SSOO","minimum":0,"maximum":127,"default_value":0,"nr1":null,"nr2":47,"value_labels":[]},{"type":"cc","name":"Sequencer Step7 OFF ON","abbr":"SSOO","minimum":0,"maximum":127,"default_value":0,"nr1":null,"nr2":48,"value_labels":[]},{"type":"cc","name":"Sequencer Step8 OFF ON","abbr":"SSOO","minimum":0,"maximum":127,"default_value":0,"nr1":null,"nr2":49,"value_labels":[]},{"type":"cc","name":"Sequencer Step1 Size","abbr":"SSSz","minimum":0,"maximum":127,"default_value":0,"nr1":null,"nr2":50,"value_labels":[]},{"type":"cc","name":"Sequencer Step2 Size","abbr":"SSSz","minimum":0,"maximum":127,"default_value":0,"nr1":null,"nr2":51,"value_labels":[]},{"type":"cc","name":"Sequencer Step3 Size","abbr":"SSSz","minimum":0,"maximum":127,"default_value":0,"nr1":null,"nr2":52,"value_labels":[]},{"type":"cc","name":"Sequencer Step4 Size","abbr":"SSSz","minimum":0,"maximum":127,"default_value":0,"nr1":null,"nr2":53,"value_labels":[]},{"type":"cc","name":"Sequencer Step5 Size","abbr":"SSSz","minimum":0,"maximum":127,"default_value":0,"nr1":null,"nr2":54,"value_labels":[]},{"type":"cc","name":"Sequencer Step6 Size","abbr":"SSSz","minimum":0,"maximum":127,"default_value":0,"nr1":null,"nr2":55,"value_labels":[]},{"type":"cc","name":"Sequencer Step7 Size","abbr":"SSSz","minimum":0,"maximum":127,"default_value":0,"nr1":null,"nr2":56,"value_labels":[]},{"type":"cc","name":"Sequencer Step8 Size","abbr":"SSSz","minimum":0,"maximum":127,"default_value":0,"nr1":null,"nr2":57,"value_labels":[]},{"type":"cc","name":"Sequence Glide","abbr":"SqGl","minimum":0,"maximum":127,"default_value":0,"nr1":null,"nr2":58,"value_labels":[]},{"type":"cc","name":"Footswitch ON","abbr":"FtOn","minimum":0,"maximum":127,"default_value":0,"nr1":null,"nr2":80,"value_labels":[]},{"type":"cc","name":"Footswitch Favorite","abbr":"FtFv","minimum":0,"maximum":127,"default_value":0,"nr1":null,"nr2":81,"value_labels":[]},{"type":"cc","name":"Footswitch Infinite","abbr":"FtIn","minimum":0,"maximum":127,"default_value":0,"nr1":null,"nr2":82,"value_labels":[]},{"type":"cc","name":"Persist","abbr":"Prss","minimum":0,"maximum":127,"default_value":0,"nr1":null,"nr2":83,"value_labels":[]},{"type":"cc","name":"Bypass ON","abbr":"ByOn","minimum":0,"maximum":127,"default_value":0,"nr1":null,"nr2":102,"value_labels":[]}],"script":null}